lana1028/__init__.py
lana1028/main.py
lana1028-0.1.6.1.dist-info/METADATA
lana1028-0.1.6.1.dist-info/WHEEL
lana1028-0.1.6.1.dist-info/top_level.txt
lana1028-0.1.6.1.dist-info/RECORD
