Metadata-Version: 2.4
Name: lana1028
Version: 0.1.6.1
Summary: LANA-1028: A custom encryption algorithm.
Author-email: Tristan <contactpgag@gmail.com>
License: MIT
Classifier: Programming Language :: Python :: 3
Classifier: License :: OSI Approved :: MIT License
Classifier: Operating System :: OS Independent
Requires-Python: >=3.12
